setup.py
datetime_process/main.py
datetime_process.egg-info/PKG-INFO
datetime_process.egg-info/SOURCES.txt
datetime_process.egg-info/dependency_links.txt
datetime_process.egg-info/top_level.txt