Metadata-Version: 2.1
Name: datetime-process
Version: 0.1
Summary: Rules date_time
Author: ndtands
Author-email: ndtan.fpt@email.com
